{
    "employees": {
      "employee": [
        {
          "id": "1",
          "firstName": "Keanu",
          "lastName": "Reeves",
          "photo": "https://xml-formatter.com/img/keanu-reeves.jpg"
        },
        {
          "id": "2",
          "firstName": "Monica",
          "lastName": "Geller",
          "photo": "https://xml-formatter.com/img/monica-geller.jpg"
        },
        {
          "id": "3",
          "firstName": "Will",
          "lastName": "Smith",
          "photo": "https://xml-formatter.com/img/will-smith.jpg"
        }
      ]
    }
  }